deepfellow/__init__.py
deepfellow/asr.py
deepfellow/base.py
deepfellow/test.py
deepfellow-0.2.3.dist-info/METADATA
deepfellow-0.2.3.dist-info/WHEEL
deepfellow-0.2.3.dist-info/top_level.txt
deepfellow-0.2.3.dist-info/RECORD
